trenchcoat/__init__.py
trenchcoat/example.py
trenchcoat-0.0.2.dist-info/METADATA
trenchcoat-0.0.2.dist-info/WHEEL
trenchcoat-0.0.2.dist-info/licenses/LICENSE
trenchcoat-0.0.2.dist-info/RECORD
