Metadata-Version: 2.3
Name: trenchcoat
Version: 0.0.2
Summary: Small example for security research
Project-URL: Homepage, https://github.com/vicenteherrera/starter-ml/llm/_security/pypi_package
Project-URL: Issues, https://github.com/vicenteherrera/starter-ml/issues
Author-email: Vicente Herrera <vicenteherrera@vicenteherrera.com>
License-File: LICENSE
Classifier: License :: OSI Approved :: MIT License
Classifier: Operating System :: OS Independent
Classifier: Programming Language :: Python :: 3
Requires-Python: >=3.8
